osam_core/__init__.py
osam_core/_contextlib.py
osam_core/_json.py
osam_core/_json_test.py
osam_core/apis.py
osam_core/apis_test.py
osam_core/types/__init__.py
osam_core/types/_annotation.py
osam_core/types/_blob.py
osam_core/types/_bounding_box.py
osam_core/types/_generate.py
osam_core/types/_image_embedding.py
osam_core/types/_model.py
osam_core/types/_prompt.py
osam_core-0.1.1.dist-info/METADATA
osam_core-0.1.1.dist-info/WHEEL
osam_core-0.1.1.dist-info/licenses/LICENSE
osam_core-0.1.1.dist-info/RECORD
